vvuq_mcp/__init__.py
vvuq_mcp/__main__.py
vvuq_mcp/auth.py
vvuq_mcp/exceptions.py
vvuq_mcp/http_api.py
vvuq_mcp/models.py
vvuq_mcp/response_types.py
vvuq_mcp/secret_manager.py
vvuq_mcp/workspace_manager_legacy.py
vvuq_mcp/feedback_models/__init__.py
vvuq_mcp/feedback_models/feedback.py
vvuq_mcp/integrations/__init__.py
vvuq_mcp/integrations/github_feedback.py
vvuq_mcp/mcp/__init__.py
vvuq_mcp/mcp/fastmcp_server.py
vvuq_mcp/mcp/server.py
vvuq_mcp/mcp/tools.py
vvuq_mcp/payments/__init__.py
vvuq_mcp/payments/crypto.py
vvuq_mcp/storage/__init__.py
vvuq_mcp/storage/neo4j_client.py
vvuq_mcp/verifiers/__init__.py
vvuq_mcp/verifiers/base.py
vvuq_mcp/verifiers/lean4.py
vvuq_mcp/workspaces/__init__.py
vvuq_mcp/workspaces/context_copier.py
vvuq_mcp/workspaces/lakefile_generator.py
vvuq_mcp/workspaces/path_generator.py
vvuq_mcp/workspaces/provisioner.py
vvuq_mcp/workspaces/workspace_cache.py
vvuq_mcp-2.1.0.dist-info/METADATA
vvuq_mcp-2.1.0.dist-info/WHEEL
vvuq_mcp-2.1.0.dist-info/entry_points.txt
vvuq_mcp-2.1.0.dist-info/top_level.txt
vvuq_mcp-2.1.0.dist-info/RECORD
