Metadata-Version: 2.4
Name: vvuq-mcp
Version: 2.1.0
Summary: Verification, Validation & Uncertainty Quantification MCP for marketplace contracts
Author-email: Dirk Englund <englund@mit.edu>
License: MIT
Requires-Python: >=3.11
Requires-Dist: aiofiles>=24.0.0
Requires-Dist: fastapi>=0.100.0
Requires-Dist: fastmcp>=2.0.0
Requires-Dist: neo4j>=6.0.0
Requires-Dist: pydantic>=2.0.0
Requires-Dist: pydantic-settings>=2.0.0
Requires-Dist: python-dotenv>=1.0.0
Requires-Dist: slowapi>=0.1.9
Requires-Dist: uvicorn>=0.30.0
Requires-Dist: httpx>=0.24.0
Requires-Dist: google-cloud-secret-manager>=2.16.0
Provides-Extra: dev
Requires-Dist: pytest>=8.0.0; extra == "dev"
Requires-Dist: pytest-asyncio>=0.23.0; extra == "dev"
Requires-Dist: pytest-cov>=6.0.0; extra == "dev"
Requires-Dist: pytest-timeout>=2.3.0; extra == "dev"
Requires-Dist: pytest-mock>=3.14.0; extra == "dev"
Requires-Dist: pytest-benchmark>=4.0.0; extra == "dev"
Requires-Dist: ruff>=0.8.0; extra == "dev"
Requires-Dist: pyright>=1.1.0; extra == "dev"
